HISTORY.rst
LICENSE
MANIFEST.in
README.rst
setup.cfg
setup.py
docs/api.rst
docs/conf.py
docs/copyright.rst
docs/history.rst
docs/index.rst
docs/usage.rst
docs/_build/html/_static/file.png
docs/_build/html/_static/forkme_right_darkblue_121621.png
docs/_build/html/_static/minus.png
docs/_build/html/_static/plus.png
haggregate/__init__.py
haggregate/cli.py
haggregate/haggregate.py
haggregate/regularize.c
haggregate.egg-info/PKG-INFO
haggregate.egg-info/SOURCES.txt
haggregate.egg-info/dependency_links.txt
haggregate.egg-info/entry_points.txt
haggregate.egg-info/not-zip-safe
haggregate.egg-info/requires.txt
haggregate.egg-info/top_level.txt
tests/__init__.py
tests/test_cli.py
tests/test_haggregate.py
tests/test_regularize.py