Metadata-Version: 2.1
Name: haggregate
Version: 3.1.0
Summary: Aggregates htimeseries to larger steps
Home-page: https://github.com/openmeteo/haggregate
Author: Antonis Christofides
Author-email: antonis@antonischristofides.com
License: GNU General Public License v3
Keywords: haggregate
Classifier: Development Status :: 4 - Beta
Classifier: Intended Audience :: Developers
Classifier: License :: OSI Approved :: GNU General Public License v3 (GPLv3)
Classifier: Natural Language :: English
Classifier: Programming Language :: Python :: 3.7
Classifier: Programming Language :: Python :: 3.8
Classifier: Programming Language :: Python :: 3.9
Classifier: Programming Language :: Python :: 3.10
Classifier: Programming Language :: Python :: 3.11
License-File: LICENSE
Requires-Dist: Click<9,>=7
Requires-Dist: htimeseries<8,>=4
